README.md
pyproject.toml
requirements.txt
tdaad/__init__.py
tdaad/anomaly_detectors.py
tdaad/persistencediagram_transformer.py
tdaad/topological_embedding.py
tdaad.egg-info/PKG-INFO
tdaad.egg-info/SOURCES.txt
tdaad.egg-info/dependency_links.txt
tdaad.egg-info/requires.txt
tdaad.egg-info/top_level.txt
tdaad/utils/__init__.py
tdaad/utils/local_elliptic_envelope.py
tdaad/utils/local_pipeline.py
tdaad/utils/remapping_functions.py
tdaad/utils/window_functions.py
tests/test_all.py