Metadata-Version: 2.4
Name: tdaad
Version: 1.4.0
Summary: Tools for anomaly detection in time series based on Topological Data Analysis
Author: Martin ROYER
Author-email: martin.royer@irt-systemx.fr
License-Expression: MPL-2.0
Project-URL: Homepage, https://irt-systemx.github.io/tdaad/
Project-URL: Documentation, https://irt-systemx.github.io/tdaad/
Project-URL: Repository, https://github.com/IRT-SystemX/tdaad
Requires-Python: >=3.12
Requires-Dist: gudhi>=3.11.0
Requires-Dist: ipykernel>=6.29.5
Requires-Dist: matplotlib>=3.7.3
Requires-Dist: numpy>=1.25.2
Requires-Dist: pandas>=2.0.3
Requires-Dist: scikit-learn>=1.3.0
Requires-Dist: scipy>=1.11.2
Requires-Dist: setuptools>=68.0.0
Requires-Dist: tqdm>=4.66.1
